{
    "resources": {
        "media": [
            {
                "name": "FONT_ROBOTO_CONDENSED_30",
                "characterRegex": "[0-9: ]",
                "type": "font",
                "file": "fonts/Roboto-Condensed-webfont.ttf"
            },
            {
                "name": "FONT_ROBOTO_CONDENSED_BOLD_38",
                "characterRegex": "[0-9 :]",
                "type": "font",
                "file": "fonts/Roboto-BoldCondensed-webfont.ttf"
            },
            {
                "name": "IMAGE_ICON",
                "menuIcon": true,
                "type": "png",
                "file": "images/watch_icon.png"
            }
        ]
    },
    "companyName": "janbobolz",
    "shortName": "Agenda",
    "uuid": "1f366804-f1d2-4288-b71a-708661777887",
    "versionCode": 10,
    "capabilities": [
        ""
    ],
    "longName": "Agenda Watchface",
    "watchapp": {
        "watchface": true
    },
    "appKeys": {},
    "versionLabel": "2.1"
}
